constituency_labeling/__init__.py
constituency_labeling/convert.py
constituency_labeling/exception.py
constituency_labeling/frontend_tree.py
constituency_labeling/label_tree.py
constituency_labeling/transform.py
constituency_labeling/tests/__init__.py
constituency_labeling/tests/test_convert.py
constituency_labeling/tests/test_frontend_tree.py
constituency_labeling/tests/test_label_tree.py
constituency_labeling/tests/test_transform.py
constituency_tree_labeling_tool-1.0.9.dist-info/LICENSE
constituency_tree_labeling_tool-1.0.9.dist-info/METADATA
constituency_tree_labeling_tool-1.0.9.dist-info/WHEEL
constituency_tree_labeling_tool-1.0.9.dist-info/top_level.txt
constituency_tree_labeling_tool-1.0.9.dist-info/RECORD
