Metadata-Version: 2.1
Name: constituency-tree-labeling-tool
Version: 1.0.9
Summary: constituency tree labeling tool
Home-page: https://github.com/geasyheart/constituency-tree-labeling-tool
Author: yuzhang
Author-email: geasyheart@163.com
License: MIT
Platform: UNKNOWN
Classifier: Programming Language :: Python :: 3
Classifier: License :: OSI Approved :: MIT License
Classifier: Operating System :: OS Independent
Requires-Python: >=3.6
Requires-Dist: nltk (==3.6.5)
Provides-Extra: full
Requires-Dist: graphviz (>=0.18.2) ; extra == 'full'
